datecond/__init__.py
datecond/__main__.py
tests/__init__.py
tests/test_daterange.py
datecond-0.1.7.dist-info/AUTHORS
datecond-0.1.7.dist-info/LICENSE
datecond-0.1.7.dist-info/METADATA
datecond-0.1.7.dist-info/WHEEL
datecond-0.1.7.dist-info/top_level.txt
datecond-0.1.7.dist-info/RECORD
