Metadata-Version: 2.1
Name: datecond
Version: 0.1.7
Summary: Parser for date range conditionals.
Home-page: https://github.com/Kwpolska/datecond
Author: Chris Warrick
Author-email: chris@chriswarrick.com
License: 3-clause BSD
Keywords: datecond
Platform: any
Classifier: Development Status :: 4 - Beta
Classifier: Topic :: Utilities
Classifier: Programming Language :: Python
Classifier: Programming Language :: Python :: 2
Classifier: Programming Language :: Python :: 2.7
Classifier: Programming Language :: Python :: 3
Classifier: Programming Language :: Python :: 3.5
Classifier: Programming Language :: Python :: 3.6
Classifier: Programming Language :: Python :: 3.7
Classifier: Programming Language :: Python :: 3.8
Requires-Dist: python-dateutil
